{
  "last_update": "2026-02-15T16:11:05.300Z",
  "total": 10,
  "episodes": [
    {
      "id": "172e17385",
      "series_id": "7bfb7e4b0",
      "series_title": "مسلسل السوق الحرة",
      "number": 1,
      "title": "مسلسل السوق الحرة الحلقة 1 الاولي",
      "image": "https://q.larozavideo.net/uploads/thumbs/172e17385-1.jpg",
      "season": 1,
      "servers": [],
      "extracted_at": "2026-02-15T16:11:02.104Z"
    },
    {
      "id": "172e17385",
      "series_id": "7bfb7e4b0",
      "series_title": "مسلسل السوق الحرة",
      "number": 1,
      "title": "مسلسل السوق الحرة الحلقة 1 الاولي",
      "image": "https://q.larozavideo.net/uploads/thumbs/172e17385-1.jpg",
      "season": 1,
      "servers": [
        {
          "name": "سيرفر 1",
          "url": "https://qq.okprime.site/embed-sypiwlhd0cbr.html"
        },
        {
          "name": "سيرفر 2",
          "url": "https://vk.com/video_ext.php?oid=889347337&id=456247094"
        },
        {
          "name": "سيرفر 3",
          "url": "https://rty1.film77.xyz/embed-gaaktokagppq.html"
        },
        {
          "name": "سيرفر 4",
          "url": "https://www.ok.ru/videoembed/11448634510042"
        }
      ],
      "extracted_at": "2026-02-15T16:11:02.104Z"
    },
    {
      "id": "ed1acc21a",
      "series_id": "1bcbf8b34",
      "series_title": "مسلسل عيلة الملك",
      "number": 1,
      "title": "مسلسل عيلة الملك الحلقة 1 الاولي",
      "image": "https://q.larozavideo.net/uploads/thumbs/ed1acc21a-1.jpg",
      "season": 1,
      "servers": [],
      "extracted_at": "2026-02-15T16:10:58.813Z"
    },
    {
      "id": "ed1acc21a",
      "series_id": "1bcbf8b34",
      "series_title": "مسلسل عيلة الملك",
      "number": 1,
      "title": "مسلسل عيلة الملك الحلقة 1 الاولي",
      "image": "https://q.larozavideo.net/uploads/thumbs/ed1acc21a-1.jpg",
      "season": 1,
      "servers": [
        {
          "name": "سيرفر 1",
          "url": "https://qq.okprime.site/embed-rs0v9rp37x5x.html"
        },
        {
          "name": "سيرفر 2",
          "url": "https://vk.com/video_ext.php?oid=888426734&id=456240991"
        },
        {
          "name": "سيرفر 3",
          "url": "https://rty1.film77.xyz/embed-najr1vt5scyn.html"
        },
        {
          "name": "سيرفر 4",
          "url": "https://vidoba.org/embed-k56eopisd3pw.html"
        },
        {
          "name": "سيرفر 5",
          "url": "https://vidspeed.org/embed-2wg87l17a3es.html"
        }
      ],
      "extracted_at": "2026-02-15T16:10:58.813Z"
    },
    {
      "id": "8dca13489",
      "series_id": "65a164752",
      "series_title": "مسلسل روج أسود",
      "number": 1,
      "title": "مسلسل روج اسود الحلقة 1 الاولي",
      "image": "https://q.larozavideo.net/uploads/thumbs/8dca13489-1.jpg",
      "season": 1,
      "servers": [],
      "extracted_at": "2026-02-15T16:10:55.842Z"
    },
    {
      "id": "8dca13489",
      "series_id": "65a164752",
      "series_title": "مسلسل روج أسود",
      "number": 1,
      "title": "مسلسل روج اسود الحلقة 1 الاولي",
      "image": "https://q.larozavideo.net/uploads/thumbs/8dca13489-1.jpg",
      "season": 1,
      "servers": [
        {
          "name": "سيرفر 1",
          "url": "https://qq.okprime.site/embed-xh3azbpab1rb.html"
        },
        {
          "name": "سيرفر 2",
          "url": "https://vk.com/video_ext.php?oid=888426734&id=456241023"
        },
        {
          "name": "سيرفر 3",
          "url": "https://rty1.film77.xyz/embed-zonun4rkgcls.html"
        }
      ],
      "extracted_at": "2026-02-15T16:10:55.841Z"
    },
    {
      "id": "f1f951efc",
      "series_id": "fd8b9e5e9",
      "series_title": "مسلسل اسأل روحك",
      "number": 1,
      "title": "مسلسل اسال روحك الحلقة 1 الاولي",
      "image": "https://q.larozavideo.net/uploads/thumbs/f1f951efc-1.jpg",
      "season": 1,
      "servers": [],
      "extracted_at": "2026-02-15T16:10:52.585Z"
    },
    {
      "id": "f1f951efc",
      "series_id": "fd8b9e5e9",
      "series_title": "مسلسل اسأل روحك",
      "number": 1,
      "title": "مسلسل اسال روحك الحلقة 1 الاولي",
      "image": "https://q.larozavideo.net/uploads/thumbs/f1f951efc-1.jpg",
      "season": 1,
      "servers": [
        {
          "name": "سيرفر 1",
          "url": "https://qq.okprime.site/embed-l04vfitad1e9.html"
        },
        {
          "name": "سيرفر 2",
          "url": "https://vk.com/video_ext.php?oid=888426734&id=456241012"
        },
        {
          "name": "سيرفر 3",
          "url": "https://rty1.film77.xyz/embed-gp8c4ezwcsex.html"
        }
      ],
      "extracted_at": "2026-02-15T16:10:52.585Z"
    },
    {
      "id": "9af1822e2",
      "series_id": "3af201230",
      "series_title": "مسلسل عرض وطلب",
      "number": 1,
      "title": "مسلسل عرض وطلب الحلقة 1 الاولي",
      "image": "https://q.larozavideo.net/uploads/thumbs/9af1822e2-1.jpg",
      "season": 1,
      "servers": [],
      "extracted_at": "2026-02-15T16:10:49.480Z"
    },
    {
      "id": "9af1822e2",
      "series_id": "3af201230",
      "series_title": "مسلسل عرض وطلب",
      "number": 1,
      "title": "مسلسل عرض وطلب الحلقة 1 الاولي",
      "image": "https://q.larozavideo.net/uploads/thumbs/9af1822e2-1.jpg",
      "season": 1,
      "servers": [
        {
          "name": "سيرفر 1",
          "url": "https://qq.okprime.site/embed-5ak5xtnq516s.html"
        },
        {
          "name": "سيرفر 2",
          "url": "https://vk.com/video_ext.php?oid=888426734&id=456240956"
        },
        {
          "name": "سيرفر 3",
          "url": "https://rty1.film77.xyz/embed-7gk6wsahhsch.html"
        },
        {
          "name": "سيرفر 4",
          "url": "https://vidoba.org/embed-1p20gzmyonyo.html"
        },
        {
          "name": "سيرفر 5",
          "url": "https://vidspeed.org/embed-wtyaemzet6o4.html"
        }
      ],
      "extracted_at": "2026-02-15T16:10:49.480Z"
    }
  ]
}