[
  {
    "id": "xaav1t6",
    "title": "المدبلج-عبقري بلا مأوى ينقذ شركتي",
    "thumbnail": "https://s2.dmcdn.net/v/b8Cpg1g5L2ibTfrC5",
    "m3u8Url": "https://cdndirector.dailymotion.com/cdn/manifest/video/xaav1t6.m3u8?sec=Vo-VuPJi00HLATQlMGxpupxRB9TqunEB6vpcqUOXLgcTfnG56s3OKR_BIxVOGIzqqgllDvIQ2tN_veymE_IoaQ&dmTs=568440&dmV1st=D597DA8A9E100B98AB51A0E1F5B4972B",
    "embedUrl": "https://www.dailymotion.com/embed/video/xaav1t6",
    "duration": 8631,
    "views": 1336,
    "uploadedAt": "2026-05-23T00:12:25.000Z",
    "timestamp": 1779495145
  },
  {
    "id": "xaav1t8",
    "title": "المدبلج-الابن المهمل يغير مصيره ليصبح تنينًا حقيقيًا",
    "thumbnail": "https://s2.dmcdn.net/v/b8Cpi1g4gzZjMNJcu",
    "m3u8Url": "https://cdndirector.dailymotion.com/cdn/manifest/video/xaav1t8.m3u8?sec=Z3iMwcKubxz2OnbWsB365p5NrgFGIoUnZ5kHNyIVc26KYLWL9xy2C0LLhhH1e5LJDiiS8fWOX11jc_7LEMkdJQ&dmTs=855881&dmV1st=427D9C31CB0B61811A1F5141C08D6979",
    "embedUrl": "https://www.dailymotion.com/embed/video/xaav1t8",
    "duration": 3312,
    "views": 43094,
    "uploadedAt": "2026-05-23T00:12:22.000Z",
    "timestamp": 1779495142
  },
  {
    "id": "xaaueya",
    "title": "مشاهدة أسيرة ملك الأسود (مدبلج)",
    "thumbnail": "https://s2.dmcdn.net/v/b85ao1g5NIz5mVGUC",
    "m3u8Url": "https://cdndirector.dailymotion.com/cdn/manifest/video/xaaueya.m3u8?sec=uPT09AEA-uTWCO8XVgflz8yxXTGOptEOsQJxd7laRpLPjoPpa2as5Sl1qZkZpugA0WutzoSxueSzuHgFeVz_uw&dmTs=371644&dmV1st=6F8099A97D5490148D9A18778B84501E",
    "embedUrl": "https://www.dailymotion.com/embed/video/xaaueya",
    "duration": 2873,
    "views": 47608,
    "uploadedAt": "2026-05-22T18:46:17.000Z",
    "timestamp": 1779475577
  },
  {
    "id": "xaatxy0",
    "title": "خالدة بلا مشاعر",
    "thumbnail": "https://s2.dmcdn.net/v/b80CO1g5NLnZbLlhx",
    "m3u8Url": "https://cdndirector.dailymotion.com/cdn/manifest/video/xaatxy0.m3u8?sec=jnK4AGICa8iPrG0uEf0d6iB6IniR_NiPo2t0PlogEbt9jyYnPDSoeKwyLt-MKnxeJzzqdsLC4Qa8rehG-U9DkQ&dmTs=726552&dmV1st=B472299821F20D56A5907AA07389ED48",
    "embedUrl": "https://www.dailymotion.com/embed/video/xaatxy0",
    "duration": 4155,
    "views": 25288,
    "uploadedAt": "2026-05-22T16:10:09.000Z",
    "timestamp": 1779466209
  },
  {
    "id": "xaaps1m",
    "title": "مشاهدة مسلسل حين ينهض الظل مدبلج",
    "thumbnail": "https://s2.dmcdn.net/v/b7Gmw1g40boFnlrMF",
    "m3u8Url": "https://cdndirector.dailymotion.com/cdn/manifest/video/xaaps1m.m3u8?sec=3-AGCpVbavoduRMsjWl8G1jm_7WugjgK4cZsQ7bBtAabjGa7nPPGKE0NqPLaHCn2xqlboanxR1aE2ANS9P-8FA&dmTs=839383&dmV1st=8F588443DDAAF3ED2A96838ED3B8CF07",
    "embedUrl": "https://www.dailymotion.com/embed/video/xaaps1m",
    "duration": 6281,
    "views": 48878,
    "uploadedAt": "2026-05-21T21:59:06.000Z",
    "timestamp": 1779400746
  },
  {
    "id": "xaaotdm",
    "title": "إياك والعبث مع هذا المتشرد! الموسم الثاني",
    "thumbnail": "https://s2.dmcdn.net/v/b75ow1g41KlZHHTx9",
    "m3u8Url": "https://cdndirector.dailymotion.com/cdn/manifest/video/xaaotdm.m3u8?sec=lxXlqq1MkyQf_vJBslQrK0QTX56i7DmfHq0H_F57J9TcNKbYYhrc-PWIHJMvAjSBD1BhhSupnIKioN_fIAxYxw&dmTs=360862&dmV1st=0F4B28DEA9D57187CCF31462126B2056",
    "embedUrl": "https://www.dailymotion.com/embed/video/xaaotdm",
    "duration": 11518,
    "views": 33396,
    "uploadedAt": "2026-05-21T17:33:11.000Z",
    "timestamp": 1779384791
  },
  {
    "id": "xaaotdo",
    "title": "[مدبلج] جنرال في المدرسة عودة القائد",
    "thumbnail": "https://s1.dmcdn.net/v/b75oy1g4BOqeTZ_7h",
    "m3u8Url": "https://cdndirector.dailymotion.com/cdn/manifest/video/xaaotdo.m3u8?sec=RIjy8XUWel7XShphPlIi05fJEoP8hi-iplZO2fP40-rDZLhY1Hu9WWQGC1TzI43A2gorpWBdWnP9MVvmVNyx4Q&dmTs=8167&dmV1st=2F0F79286DA23DF018BF7EF3A83D2E41",
    "embedUrl": "https://www.dailymotion.com/embed/video/xaaotdo",
    "duration": 8458,
    "views": 3221,
    "uploadedAt": "2026-05-21T17:27:08.000Z",
    "timestamp": 1779384428
  },
  {
    "id": "xaaotdq",
    "title": "لعبة استعادة المجد",
    "thumbnail": "https://s2.dmcdn.net/v/b75o-1g41bX8p3_Xn",
    "m3u8Url": "https://cdndirector.dailymotion.com/cdn/manifest/video/xaaotdq.m3u8?sec=0OSzCGRJm6LZuFH6PxH787rgk_52MoOubSb0bjN6cIrqXz_s3nSCj6M7Rla2KuMxMxc5oJKBfqFhN7SJM34htg&dmTs=588551&dmV1st=59750EE12DF63AC0C503C759FE293C81",
    "embedUrl": "https://www.dailymotion.com/embed/video/xaaotdq",
    "duration": 5183,
    "views": 25575,
    "uploadedAt": "2026-05-21T17:07:21.000Z",
    "timestamp": 1779383241
  },
  {
    "id": "xaaotdk",
    "title": "[مدبلج]مناورة الخصي",
    "thumbnail": "https://s1.dmcdn.net/v/b75ou1g4BkdWuc-G4",
    "m3u8Url": "https://cdndirector.dailymotion.com/cdn/manifest/video/xaaotdk.m3u8?sec=RUqVF6oUDhjR99sF7EmPNJSxdMXVFu-g-QrlWWOZV-JFsZCq1MfbLHJM-MqDvvhaJ6lYK86BznWf4VYfTEkhmQ&dmTs=723879&dmV1st=E3D1A10A0712D0508E859C4DA3E3E3FD",
    "embedUrl": "https://www.dailymotion.com/embed/video/xaaotdk",
    "duration": 8345,
    "views": 3383,
    "uploadedAt": "2026-05-21T17:06:09.000Z",
    "timestamp": 1779383169
  },
  {
    "id": "xaanmpc",
    "title": "عقد بلا حب",
    "thumbnail": "https://s1.dmcdn.net/v/b6uIm1g3vk5unfpeD",
    "m3u8Url": "https://cdndirector.dailymotion.com/cdn/manifest/video/xaanmpc.m3u8?sec=DW8JBBo7t0xxGVmascSw0OXAGbwUsb_9Lvcu2gzKDJIWcFMfL0zMiuBGJSRFXy5xx22UtDVtkBsGBpP9fv0JAg&dmTs=484822&dmV1st=95F3D58FE9EF26EB2BB336129F63EEA0",
    "embedUrl": "https://www.dailymotion.com/embed/video/xaanmpc",
    "duration": 6161,
    "views": 42740,
    "uploadedAt": "2026-05-21T11:34:46.000Z",
    "timestamp": 1779363286
  },
  {
    "id": "xaam372",
    "title": "تكفير الذنب بعد سبع سنوات",
    "thumbnail": "https://s2.dmcdn.net/v/b6ckk1g3vk8LMhT8m",
    "m3u8Url": "https://cdndirector.dailymotion.com/cdn/manifest/video/xaam372.m3u8?sec=mVPEj2JslC3woQFvUDVzCQngMoAvxfuCH-y2_AkJRF0HQN0FCduyEonC0eVxLDvhu1eKkmnmuGiT-NgFYTB2_Q&dmTs=405862&dmV1st=1883EA11E0852813189B9DAE4BD66200",
    "embedUrl": "https://www.dailymotion.com/embed/video/xaam372",
    "duration": 8075,
    "views": 42007,
    "uploadedAt": "2026-05-21T04:57:56.000Z",
    "timestamp": 1779339476
  },
  {
    "id": "xaam374",
    "title": "عودة ملك التل الذهبي",
    "thumbnail": "https://s2.dmcdn.net/v/b6ckm1g3jULZJAYOA",
    "m3u8Url": "https://cdndirector.dailymotion.com/cdn/manifest/video/xaam374.m3u8?sec=saeZo91LSmSIyU5sxyLSQeYujdoXiji77JYKAcLtwHv_VY8D8CXsIDKeDh3qz_qOFoOIETsUKci4NGS4ojx2KA&dmTs=546486&dmV1st=422178D9104D8C9C1866628C3541FA10",
    "embedUrl": "https://www.dailymotion.com/embed/video/xaam374",
    "duration": 7397,
    "views": 16761,
    "uploadedAt": "2026-05-21T04:52:50.000Z",
    "timestamp": 1779339170
  },
  {
    "id": "xaah2yk",
    "title": "امي لم اعد اكذب",
    "thumbnail": "https://s2.dmcdn.net/v/b5jiy1g41fWxtyNL1",
    "m3u8Url": "https://cdndirector.dailymotion.com/cdn/manifest/video/xaah2yk.m3u8?sec=AV1ErOIItNda89goUNqZiBqY-NjgGtEzHWVO4z3OC9s0NWwxre7QghOZcQ8fs8NjTnb8ZXI1GXgYOhlLTVrx5A&dmTs=565521&dmV1st=49C9FE9AFAE79068D1D30EC28CA3E226",
    "embedUrl": "https://www.dailymotion.com/embed/video/xaah2yk",
    "duration": 2885,
    "views": 42487,
    "uploadedAt": "2026-05-20T16:49:51.000Z",
    "timestamp": 1779295791
  },
  {
    "id": "xaageq6",
    "title": "عهد النسيان",
    "thumbnail": "https://s2.dmcdn.net/v/b5c2E1g41yXpQ-pb-",
    "m3u8Url": "https://cdndirector.dailymotion.com/cdn/manifest/video/xaageq6.m3u8?sec=_Quy6_V3jBAQ8LTZ_USWmFV6jDJG2st04w3n2g5FYnBKeyvGj7fITzFICDGSniQsxJ9EXTvFw4DVH1hDdAhASA&dmTs=690881&dmV1st=0E0947AF196C8DAE1A3C88ACF440C111",
    "embedUrl": "https://www.dailymotion.com/embed/video/xaageq6",
    "duration": 8673,
    "views": 3342,
    "uploadedAt": "2026-05-20T15:47:13.000Z",
    "timestamp": 1779292033
  },
  {
    "id": "xaabc5e",
    "title": "قوة تنين العاصمة",
    "thumbnail": "https://s2.dmcdn.net/v/b4iH21g4It7SwWDpC",
    "m3u8Url": "https://cdndirector.dailymotion.com/cdn/manifest/video/xaabc5e.m3u8?sec=J0mJpbAamkDlI6IWSJjUqsgoNjqjEkcnM6HgVk9c3N5q6gj8fAcuQIA86HgmvbJkInQ3zqueSaj9MH15iKSZHA&dmTs=155921&dmV1st=3F348A4A7FD104FDB10CB1A34C771800",
    "embedUrl": "https://www.dailymotion.com/embed/video/xaabc5e",
    "duration": 7613,
    "views": 40107,
    "uploadedAt": "2026-05-20T06:00:10.000Z",
    "timestamp": 1779256810
  },
  {
    "id": "xaaahn6",
    "title": "عقدت عليها لأعذبها",
    "thumbnail": "https://s2.dmcdn.net/v/b4YdI1g4F3Y6MHAXL",
    "m3u8Url": "https://cdndirector.dailymotion.com/cdn/manifest/video/xaaahn6.m3u8?sec=xcBoTkGZE-7crTY319KGNxhGf9a0UdzGpJWhJIbIhXg0JTAITsWG7p9MYgGTof1B3cLTOajPV5WC0dt1yWoTng&dmTs=19502&dmV1st=53E5606EE0113EB6F9444A0E554A6609",
    "embedUrl": "https://www.dailymotion.com/embed/video/xaaahn6",
    "duration": 1842,
    "views": 37988,
    "uploadedAt": "2026-05-20T03:06:01.000Z",
    "timestamp": 1779246361
  },
  {
    "id": "xaaahn4",
    "title": "صقيع الصورة القديمة",
    "thumbnail": "https://s1.dmcdn.net/v/b4YdG1g4EoiuDZs1q",
    "m3u8Url": "https://cdndirector.dailymotion.com/cdn/manifest/video/xaaahn4.m3u8?sec=RoHsrYLIV0e0SIFDjB9z_E_dsuoglfUPOIf81fXWs84g0HXgcshH86jc7HikVUG8h96bLen_v8Mz0nCUjHl_Ww&dmTs=21714&dmV1st=241049D9792C2F524B5B55B26745297A",
    "embedUrl": "https://www.dailymotion.com/embed/video/xaaahn4",
    "duration": 6081,
    "views": 27928,
    "uploadedAt": "2026-05-20T03:05:59.000Z",
    "timestamp": 1779246359
  },
  {
    "id": "xaaa1vw",
    "title": "من يسرق كودي سأسرق مستقبله",
    "thumbnail": "https://s2.dmcdn.net/v/b4TeC1g3d0sdgSRUc",
    "m3u8Url": "https://cdndirector.dailymotion.com/cdn/manifest/video/xaaa1vw.m3u8?sec=zfRT69Qo9HihO4KfXt6rSueUFAKWbSuLNSyIPXANzeyoxCs6IzY_1Ro2TRb6P7Ri_DCHeOWnpX2uYRpJDBPiUQ&dmTs=248648&dmV1st=DA192B49FD303832B5FFC9F365F7420A",
    "embedUrl": "https://www.dailymotion.com/embed/video/xaaa1vw",
    "duration": 3066,
    "views": 19120,
    "uploadedAt": "2026-05-19T21:51:15.000Z",
    "timestamp": 1779227475
  },
  {
    "id": "xaa9srs",
    "title": "صراع الرتب",
    "thumbnail": "https://s1.dmcdn.net/v/b4Qle1g3VjXbOx06w",
    "m3u8Url": "https://cdndirector.dailymotion.com/cdn/manifest/video/xaa9srs.m3u8?sec=QNDlqrNozbG-8dnggCBuQYCjc5fyFDqZDF8NgoU4ZD0TopDd27STlTRzxDmz2YeQivF-hDDhMMc85amA-VHsQg&dmTs=465102&dmV1st=53782CB3B9D34FD829A8D0FD81C7044C",
    "embedUrl": "https://www.dailymotion.com/embed/video/xaa9srs",
    "duration": 3565,
    "views": 31631,
    "uploadedAt": "2026-05-19T19:12:09.000Z",
    "timestamp": 1779217929
  },
  {
    "id": "xaa8mhg",
    "title": "ترتقي في العصر الحديث بسر الأساطير",
    "thumbnail": "https://s2.dmcdn.net/v/b4DNK1g38CiSAWMxA",
    "m3u8Url": "https://cdndirector.dailymotion.com/cdn/manifest/video/xaa8mhg.m3u8?sec=AvNcTw0fDNHu7mX-Uz4ySxXTb7J3Mi7j5IVjqlHt7GAqGXXmQLTx0k5KPszSQp_rIlXfQLBGlMiAdSI8n5j3aQ&dmTs=527912&dmV1st=B9A554729207BE0E757D9DEC2E8EF642",
    "embedUrl": "https://www.dailymotion.com/embed/video/xaa8mhg",
    "duration": 8012,
    "views": 36542,
    "uploadedAt": "2026-05-19T13:27:22.000Z",
    "timestamp": 1779197242
  },
  {
    "id": "xaa8k9i",
    "title": "الترداد الساحر",
    "thumbnail": "https://s1.dmcdn.net/v/b4CgM1g41fSp9Y5kM",
    "m3u8Url": "https://cdndirector.dailymotion.com/cdn/manifest/video/xaa8k9i.m3u8?sec=LnIgJRSiSH6skaz8kwDT3Iu734TGI6xkMUZFWiasmxZJZ-OYtSCgi2tRQlzxfpTyg84kfrh891T3KfiNX3WPeQ&dmTs=896414&dmV1st=A70E1CCD7BF75D38FFC359D2B03E824C",
    "embedUrl": "https://www.dailymotion.com/embed/video/xaa8k9i",
    "duration": 8062,
    "views": 49249,
    "uploadedAt": "2026-05-19T13:23:32.000Z",
    "timestamp": 1779197012
  },
  {
    "id": "xaa8k9e",
    "title": "مهووس بك وحدك",
    "thumbnail": "https://s1.dmcdn.net/v/b4CgI1g3viO_kGxV0",
    "m3u8Url": "https://cdndirector.dailymotion.com/cdn/manifest/video/xaa8k9e.m3u8?sec=XSv_roNbjOU9K1IVW3EKtt_p-6c1iCMyCi-x4O-uLPkl05WdSSSc4j8FNftvoMqz7uge7gVXXJkQgpFjUSVchQ&dmTs=553631&dmV1st=77DCA2B86C15F5911E62B3EA689CB2B4",
    "embedUrl": "https://www.dailymotion.com/embed/video/xaa8k9e",
    "duration": 7681,
    "views": 10878,
    "uploadedAt": "2026-05-19T13:17:13.000Z",
    "timestamp": 1779196633
  },
  {
    "id": "xaa8k98",
    "title": "خرج عن الإطار وغاص في عشقي",
    "thumbnail": "https://s2.dmcdn.net/v/b4CgC1g3viPaZOh4u",
    "m3u8Url": "https://cdndirector.dailymotion.com/cdn/manifest/video/xaa8k98.m3u8?sec=k5b37-nuJO5P552_SjrEilVBcACQZnzPtkD4Xs1-qxW0NPcMh0OdS2lK5IDPIM2-PpY2AEjRq8yPdb0kIRX78A&dmTs=120187&dmV1st=6F02D21F6B97A91EE49F9FC2E48B507F",
    "embedUrl": "https://www.dailymotion.com/embed/video/xaa8k98",
    "duration": 7938,
    "views": 13532,
    "uploadedAt": "2026-05-19T13:16:09.000Z",
    "timestamp": 1779196569
  },
  {
    "id": "xaa8k9o",
    "title": "هو جامح جدًا",
    "thumbnail": "https://s1.dmcdn.net/v/b4CgS1g41yntXmaj8",
    "m3u8Url": "https://cdndirector.dailymotion.com/cdn/manifest/video/xaa8k9o.m3u8?sec=Zsei87l4PuxO8iDZhRdXvAxN1xZFEijNPEj062IyV-ENDKdy_mxFD2IU6-xYK9fDEx3KGBnBrseOZzgbqhlx8w&dmTs=39317&dmV1st=CC922EF210F53F78FA7DD9FE1600E960",
    "embedUrl": "https://www.dailymotion.com/embed/video/xaa8k9o",
    "duration": 9086,
    "views": 41025,
    "uploadedAt": "2026-05-19T13:14:37.000Z",
    "timestamp": 1779196477
  },
  {
    "id": "xaa8k96",
    "title": "لزوجتي كثير من الحيل",
    "thumbnail": "https://s1.dmcdn.net/v/b4CgA1g41z5JGvv2C",
    "m3u8Url": "https://cdndirector.dailymotion.com/cdn/manifest/video/xaa8k96.m3u8?sec=Q_JOaxJENkEJCAjdpoatsufkf86Y5Efv9n2uxL_5HUGuhNBahWuLh1qzTqQeQkwvGppcOcsX_OQtwLlwgmKZzg&dmTs=119353&dmV1st=EF2C7CEDF61BCE9732770C9848CDC07A",
    "embedUrl": "https://www.dailymotion.com/embed/video/xaa8k96",
    "duration": 7059,
    "views": 35150,
    "uploadedAt": "2026-05-19T13:12:08.000Z",
    "timestamp": 1779196328
  },
  {
    "id": "xaa8k9q",
    "title": "بعد خيانة يفقد حبه إلى الأبد",
    "thumbnail": "https://s2.dmcdn.net/v/b4CgU1g41fdEbOmji",
    "m3u8Url": "https://cdndirector.dailymotion.com/cdn/manifest/video/xaa8k9q.m3u8?sec=P1637uJ-maK-pY7NVYJMlYm-iPmrjL1tuDWqzM48KaQB4Y2-cUWEFxoxA4xLzgK0ZaPT1INzu_UUYTvMqofK3g&dmTs=966762&dmV1st=3132E238B59B1DEBC9E67B54F4BDEDAC",
    "embedUrl": "https://www.dailymotion.com/embed/video/xaa8k9q",
    "duration": 7094,
    "views": 46531,
    "uploadedAt": "2026-05-19T13:12:04.000Z",
    "timestamp": 1779196324
  },
  {
    "id": "xaa8k9g",
    "title": "عندما يصل الحب",
    "thumbnail": "https://s2.dmcdn.net/v/b4CgK1g3viPiGVeAU",
    "m3u8Url": "https://cdndirector.dailymotion.com/cdn/manifest/video/xaa8k9g.m3u8?sec=7q0A342KbT3XVsITwre-NjOsWxfqzeuadb_aN3AH9h1ziZooQQ-8yYZgiqObXqfD3DIIIsc2T_BG9M9oyHuckA&dmTs=652046&dmV1st=F5AD0A0E51684664A9DA4BC6380C1504",
    "embedUrl": "https://www.dailymotion.com/embed/video/xaa8k9g",
    "duration": 6699,
    "views": 20042,
    "uploadedAt": "2026-05-19T13:11:58.000Z",
    "timestamp": 1779196318
  },
  {
    "id": "xaa8k9a",
    "title": "تواعدنا",
    "thumbnail": "https://s2.dmcdn.net/v/b4CgE1g4uPAtze0_A",
    "m3u8Url": "https://cdndirector.dailymotion.com/cdn/manifest/video/xaa8k9a.m3u8?sec=3Mrg4hfdhCZSgy0tXmuEdcT2NAawNYiX0sp8SFQNjHe6d0_DrhgPLWiWBvL63a0RyKk9zPgymWUHVK5D4avEpg&dmTs=345206&dmV1st=235E998762E94A0D1FB700021A6656B7",
    "embedUrl": "https://www.dailymotion.com/embed/video/xaa8k9a",
    "duration": 6908,
    "views": 32368,
    "uploadedAt": "2026-05-19T13:08:01.000Z",
    "timestamp": 1779196081
  },
  {
    "id": "xaa8k9k",
    "title": "إِدمانها في الليل",
    "thumbnail": "https://s1.dmcdn.net/v/b4CgO1g3viQkD-rZU",
    "m3u8Url": "https://cdndirector.dailymotion.com/cdn/manifest/video/xaa8k9k.m3u8?sec=8TlLUfetmo_l_XcpcOn0tUW2amxngJn4unej9gAcoUysDca0mqUAf-pr-wsjjKJdG5KJ97FgdctEKD3mw6qpCg&dmTs=365639&dmV1st=2716EF5DF9B521993BA96FC756CE57C0",
    "embedUrl": "https://www.dailymotion.com/embed/video/xaa8k9k",
    "duration": 5514,
    "views": 20702,
    "uploadedAt": "2026-05-19T13:06:59.000Z",
    "timestamp": 1779196019
  },
  {
    "id": "xaa8k9c",
    "title": "لا أحب إلا إياها",
    "thumbnail": "https://s1.dmcdn.net/v/b4CgG1g41dVxCNxfg",
    "m3u8Url": "https://cdndirector.dailymotion.com/cdn/manifest/video/xaa8k9c.m3u8?sec=W28lNRhnSx_gb56ObrSWEUEJIzaDg9MpRZs0vgirgGmHDT3v7GgjzH4pvTJjTWgpHXK2hFzdZSlfTIJLCVl06g&dmTs=426968&dmV1st=F3E7E3F061AB52E93B11297B9A74C515",
    "embedUrl": "https://www.dailymotion.com/embed/video/xaa8k9c",
    "duration": 8210,
    "views": 36185,
    "uploadedAt": "2026-05-19T13:06:44.000Z",
    "timestamp": 1779196004
  },
  {
    "id": "xaa8mhe",
    "title": "زوجي الجديد من الأثرياء",
    "thumbnail": "https://s1.dmcdn.net/v/b4DNI1g41fd7CFCu5",
    "m3u8Url": "https://cdndirector.dailymotion.com/cdn/manifest/video/xaa8mhe.m3u8?sec=iZ7Vy1JAKFWh-iHFKf7oUJkWZDkDG5zRN2nYge7aQSb4Xl6aC7XazkD4b8DvxQMzVn0xIKuRRz-YYuLagy5miA&dmTs=174681&dmV1st=2E523510408721DD7336786539C4DA93",
    "embedUrl": "https://www.dailymotion.com/embed/video/xaa8mhe",
    "duration": 6417,
    "views": 26299,
    "uploadedAt": "2026-05-19T13:06:28.000Z",
    "timestamp": 1779195988
  },
  {
    "id": "xaa8dn8",
    "title": "صقيع الصورة القديمة",
    "thumbnail": "https://s1.dmcdn.net/v/b4AaK1g41dVoOS760",
    "m3u8Url": "https://cdndirector.dailymotion.com/cdn/manifest/video/xaa8dn8.m3u8?sec=z2Oer2K6eoXtgPuBTg-JUUkH60VABC54f58f_Z8inD20kqxkARV4zXtP-Qaje1CAJm91gvEx1mxkkUlUHaQKNg&dmTs=263376&dmV1st=C6005C24D267CE035F738D18F676E525",
    "embedUrl": "https://www.dailymotion.com/embed/video/xaa8dn8",
    "duration": 5924,
    "views": 33359,
    "uploadedAt": "2026-05-19T12:24:17.000Z",
    "timestamp": 1779193457
  },
  {
    "id": "xaa7r7k",
    "title": "النظام الخارق يمنحني 3 فتيات (مدبلج)",
    "thumbnail": "https://s2.dmcdn.net/v/b43U01g3viTJ3Q4lr",
    "m3u8Url": "https://cdndirector.dailymotion.com/cdn/manifest/video/xaa7r7k.m3u8?sec=VFNL-GPhglyXijjqFkdZcnL0SUdRIPeYE4_9W9ejoyCg0EU5D1uBgbIrtu83EaT0MBowyieoaM5L0G_cJ7XYJQ&dmTs=165294&dmV1st=5A890E5F916BF49C65F0A5CDF3DDEE8C",
    "embedUrl": "https://www.dailymotion.com/embed/video/xaa7r7k",
    "duration": 3937,
    "views": 34741,
    "uploadedAt": "2026-05-19T09:24:03.000Z",
    "timestamp": 1779182643
  },
  {
    "id": "xaa7r7o",
    "title": "النظام الخارق يمنحني 3 فتيات",
    "thumbnail": "https://s1.dmcdn.net/v/b43U41g41dVdXDSs9",
    "m3u8Url": "https://cdndirector.dailymotion.com/cdn/manifest/video/xaa7r7o.m3u8?sec=2w54yTVa73p_5ezQIDeHHvqacTXbPj9apV5loTxTC8O0Qh-_3sm6kDEWH153mxk5H1_WHua_nAI8i60_LqkEJw&dmTs=471750&dmV1st=F4662A215D79A618F3DFC77C67725B37",
    "embedUrl": "https://www.dailymotion.com/embed/video/xaa7r7o",
    "duration": 3987,
    "views": 34544,
    "uploadedAt": "2026-05-19T09:23:58.000Z",
    "timestamp": 1779182638
  },
  {
    "id": "xaa7r7w",
    "title": "سيد الخلود في المدينة لا يقهر منذ النزول",
    "thumbnail": "https://s2.dmcdn.net/v/b43UC1g41Lp_FhWEy",
    "m3u8Url": "https://cdndirector.dailymotion.com/cdn/manifest/video/xaa7r7w.m3u8?sec=Y4K9G2spqKPNjSr1S8jM8g-h-MWbNeZf8_pFIaC_XQNDMMIQQjugLBOlwXW1G7dSZy7IECA_dawhSt5ZILftRQ&dmTs=813856&dmV1st=2EF4326CFBCA217AADDF2D4A5FA1A064",
    "embedUrl": "https://www.dailymotion.com/embed/video/xaa7r7w",
    "duration": 9266,
    "views": 18280,
    "uploadedAt": "2026-05-19T09:23:49.000Z",
    "timestamp": 1779182629
  }
]