[
  {
    "id": "xa3e38e",
    "title": "[مدبلج]القبطان الصغير",
    "thumbnail": "https://s2.dmcdn.net/v/aOLBU1foscCwPMtXD",
    "m3u8Url": "https://cdndirector.dailymotion.com/cdn/manifest/video/xa3e38e.m3u8?sec=sj3lhxmjdTMsvB1GG7hrjsjCDGglCAxBqi8lmO44rzunQtq9fDQ17q-vuRBoymy0fh7iw_few9xHaGlhqbPQIA&dmTs=211423&dmV1st=CCCBC51AED16D887259AF7D806855442",
    "embedUrl": "https://www.dailymotion.com/embed/video/xa3e38e",
    "duration": 5204,
    "views": 32879,
    "uploadedAt": "2026-03-26T20:57:33.000Z",
    "timestamp": 1774558653
  },
  {
    "id": "xa3e1re",
    "title": "ملك القناصين",
    "thumbnail": "https://s2.dmcdn.net/v/aOKjg1g41d1iDg4ae",
    "m3u8Url": "https://cdndirector.dailymotion.com/cdn/manifest/video/xa3e1re.m3u8?sec=NVANOWhWIAmbz2jW4sOShqf1d9XHCp5DUPZ5G5tVNAv-R_Nb41jAD-wkqnYQqiDyXxYTC24SoOx6e84GT6C3Qg&dmTs=226205&dmV1st=7AEB655F63F4DC9FF433F8979FDAD83E",
    "embedUrl": "https://www.dailymotion.com/embed/video/xa3e1re",
    "duration": 4322,
    "views": 8195,
    "uploadedAt": "2026-03-26T20:19:35.000Z",
    "timestamp": 1774556375
  },
  {
    "id": "xa3dxsw",
    "title": "أبي، أنا نجمة حظك",
    "thumbnail": "https://s2.dmcdn.net/v/aOJTW1g41fAoORKVr",
    "m3u8Url": "https://cdndirector.dailymotion.com/cdn/manifest/video/xa3dxsw.m3u8?sec=fSac15LYZFyp9q_ohByUtz6HTp-mdw5Zgs5cMxj5FRvzBnLgVu3tjd6mXfzfXoi4wH5kvEhY1UYaTG1Uifl5Pg&dmTs=213842&dmV1st=6D596AC4355D7A05EA5F51E33F7AA826",
    "embedUrl": "https://www.dailymotion.com/embed/video/xa3dxsw",
    "duration": 4836,
    "views": 44681,
    "uploadedAt": "2026-03-26T19:30:46.000Z",
    "timestamp": 1774553446
  },
  {
    "id": "xa3d076",
    "title": "خطيبة ابني وقعت في المصيدة",
    "thumbnail": "https://s2.dmcdn.net/v/aO8r21g3xz4wAaxYP",
    "m3u8Url": "https://cdndirector.dailymotion.com/cdn/manifest/video/xa3d076.m3u8?sec=PscWLpJZgk3L1DTpPr80svfziOEluAxX-MGkYUgl6HQIdJIp4rTTwo5Gw8FjEV_JIgLAIwWDQw_zrpeEP1OFWQ&dmTs=859860&dmV1st=E361BE97769A07247E56320F003C07CA",
    "embedUrl": "https://www.dailymotion.com/embed/video/xa3d076",
    "duration": 5916,
    "views": 14023,
    "uploadedAt": "2026-03-26T14:13:02.000Z",
    "timestamp": 1774534382
  },
  {
    "id": "xa3cuoe",
    "title": "أسطورة التحف",
    "thumbnail": "https://s1.dmcdn.net/v/aO75E1g41SWkTsJhp",
    "m3u8Url": "https://cdndirector.dailymotion.com/cdn/manifest/video/xa3cuoe.m3u8?sec=QRZO8kJQO6yi_xEhfRxPnfIaz5N8UgA6Ps5_233eJAcqEcoE4sgNBYrw_bj-ofH-dF8dWr5rT5aPi1vSlDpcLw&dmTs=528972&dmV1st=BA98BC84259FEB7F85DD0A5C2C2D70DA",
    "embedUrl": "https://www.dailymotion.com/embed/video/xa3cuoe",
    "duration": 6137,
    "views": 19286,
    "uploadedAt": "2026-03-26T13:07:25.000Z",
    "timestamp": 1774530445
  },
  {
    "id": "xa3b804",
    "title": "بين عالمين",
    "thumbnail": "https://s1.dmcdn.net/v/aNqX41g3omededluq",
    "m3u8Url": "https://cdndirector.dailymotion.com/cdn/manifest/video/xa3b804.m3u8?sec=HbAJTbqwGriVH2oi4rWThMaA8t3ksC9VlG0pymDWPe4Uvzqj3vzE2YgFp1fylnvmckwLwOLDAOZxUe0ASDd3Pg&dmTs=208357&dmV1st=F9D567753ADF017FBD3F9B1774998D71",
    "embedUrl": "https://www.dailymotion.com/embed/video/xa3b804",
    "duration": 6564,
    "views": 4396,
    "uploadedAt": "2026-03-26T01:46:53.000Z",
    "timestamp": 1774489613
  },
  {
    "id": "xa398ha",
    "title": "- (مدبلج) أنينُ السيوف... ووجعُ القلوب",
    "thumbnail": "https://s2.dmcdn.net/v/aNTuk1g41-XcogjM0",
    "m3u8Url": "https://cdndirector.dailymotion.com/cdn/manifest/video/xa398ha.m3u8?sec=n6qPusVr32z0duBoZMa4Ab7_FInM7lacF8y4l5F1NXZDymSh-qDLAmrvh69uaW5Q6RlBOCkF_75KfASB_laJEQ&dmTs=988421&dmV1st=BECC0526530F06C6D4954AC68ED508D9",
    "embedUrl": "https://www.dailymotion.com/embed/video/xa398ha",
    "duration": 6132,
    "views": 25953,
    "uploadedAt": "2026-03-25T11:20:59.000Z",
    "timestamp": 1774437659
  },
  {
    "id": "xa2v4iu",
    "title": "المعادلة الصفرية",
    "thumbnail": "https://s2.dmcdn.net/v/aKzAc1g3__WwoLGS4",
    "m3u8Url": "https://cdndirector.dailymotion.com/cdn/manifest/video/xa2v4iu.m3u8?sec=-OZ1GfPrBtnHT0q4xHttnG_82E37WEl84Z0naKEFBuw7KjByfWHvtCcmChSQ10-_5-goaJ7bmHZ7waLzTSjBwQ&dmTs=728815&dmV1st=E530D68F1968DC9F484920AE9B0B50C4",
    "embedUrl": "https://www.dailymotion.com/embed/video/xa2v4iu",
    "duration": 5021,
    "views": 16744,
    "uploadedAt": "2026-03-21T11:00:00.000Z",
    "timestamp": 1774090800
  },
  {
    "id": "xa2v1g4",
    "title": "الوجه الآخر  للطيب",
    "thumbnail": "https://s1.dmcdn.net/v/aKyCK1g41kmBFA9bS",
    "m3u8Url": "https://cdndirector.dailymotion.com/cdn/manifest/video/xa2v1g4.m3u8?sec=rPFtOEmJdmSglSouQIq4DSsMswWEV5vavQKDfsyp_7jOSvs9ks_8jKljHKt8j0EdYILkNNRyvQNhcQfqLUQ19g&dmTs=591877&dmV1st=E2B799084988A1AEAA4B4A6CF86A9B75",
    "embedUrl": "https://www.dailymotion.com/embed/video/xa2v1g4",
    "duration": 6476,
    "views": 3779,
    "uploadedAt": "2026-03-21T10:10:46.000Z",
    "timestamp": 1774087846
  },
  {
    "id": "xa2u1am",
    "title": "--2--مدبلج في قلب الظلام عاد حاملا ثمن كل الخيانات",
    "thumbnail": "https://s2.dmcdn.net/v/aKmmE1fnYCTWPl1ta",
    "m3u8Url": "https://cdndirector.dailymotion.com/cdn/manifest/video/xa2u1am.m3u8?sec=lkvKH1nrigDPYG3vWLLYKBWPx64FsAOWq7d5fcslRVy8sO1O5NUU2qztE3PZLD4jVwooHwwRngNMjRHXEcOXZA&dmTs=289663&dmV1st=618107EB9C7D6098DFDAFAA249662B5D",
    "embedUrl": "https://www.dailymotion.com/embed/video/xa2u1am",
    "duration": 3436,
    "views": 1494,
    "uploadedAt": "2026-03-20T22:53:46.000Z",
    "timestamp": 1774047226
  },
  {
    "id": "xa2tq3a",
    "title": "--1--مدبلج في قلب الظلام عاد حاملا ثمن كل الخيانات",
    "thumbnail": "https://s2.dmcdn.net/v/aKjDM1g3VFRbQlufz",
    "m3u8Url": "https://cdndirector.dailymotion.com/cdn/manifest/video/xa2tq3a.m3u8?sec=ptOEPRYTRLnV9nIZJLVqmh4bs0LYtS1Xux46dd8h62AL2YKDmMM2WJg3fI_9gr4hxICbUcQPzIWyAoz1rDq6Aw&dmTs=939219&dmV1st=3D25628061ADDD0CE32548C7EC08D9DE",
    "embedUrl": "https://www.dailymotion.com/embed/video/xa2tq3a",
    "duration": 3171,
    "views": 2151,
    "uploadedAt": "2026-03-20T18:36:50.000Z",
    "timestamp": 1774031810
  },
  {
    "id": "xa2sxf4",
    "title": "بعمر الجبال والأنهار",
    "thumbnail": "https://s1.dmcdn.net/v/aKa8m1fnRZ-kEP4bF",
    "m3u8Url": "https://cdndirector.dailymotion.com/cdn/manifest/video/xa2sxf4.m3u8?sec=yQckKA0D_-K24DYLSIEpjDnnHj7gk6-nUUobWODYe3GrTR1L6nvOeKN7mG5dOu2dXMPDEy8z4b1baSy-XIZuSw&dmTs=727080&dmV1st=DE5D9B583320B8EF6C34CAB4C94E1A6F",
    "embedUrl": "https://www.dailymotion.com/embed/video/xa2sxf4",
    "duration": 6300,
    "views": 15286,
    "uploadedAt": "2026-03-20T12:36:13.000Z",
    "timestamp": 1774010173
  },
  {
    "id": "xa2stj6",
    "title": "بقهر الشيطانات أزداد قوةً… وسأحكم العوالم الثلاثة",
    "thumbnail": "https://s2.dmcdn.net/v/aKYw21g41iSQ5EFa8",
    "m3u8Url": "https://cdndirector.dailymotion.com/cdn/manifest/video/xa2stj6.m3u8?sec=xyCSgKaAMiQNWmnHi-6pwupOkoOCFgr6GayaTKXg2SWTPxhEx05eJYytBrAgyOB9ER1EZiYkOjNBdYLmS8lPcQ&dmTs=842839&dmV1st=C8A665B6D14B775BA3636DAFDD069CB0",
    "embedUrl": "https://www.dailymotion.com/embed/video/xa2stj6",
    "duration": 4291,
    "views": 48588,
    "uploadedAt": "2026-03-20T11:41:36.000Z",
    "timestamp": 1774006896
  },
  {
    "id": "xa2s5gq",
    "title": "الإمبراطور الطائش الذي أنقذ عرشه بالزوجات",
    "thumbnail": "https://s2.dmcdn.net/v/aKRIg1g3XVfy8lQm8",
    "m3u8Url": "https://cdndirector.dailymotion.com/cdn/manifest/video/xa2s5gq.m3u8?sec=BcK0VzCXW7p_jtigL5QXxV5UFvx6ECp-q0xX3TT_-zECC9cGcQkBgIPr_3WDpkJRj8srHeF6O76XDoDW38e74Q&dmTs=488053&dmV1st=0DF60D5469A277D6E1950100D3D01A02",
    "embedUrl": "https://www.dailymotion.com/embed/video/xa2s5gq",
    "duration": 6443,
    "views": 19024,
    "uploadedAt": "2026-03-20T07:02:29.000Z",
    "timestamp": 1773990149
  },
  {
    "id": "xa2s17q",
    "title": "زوجي المتفرغ",
    "thumbnail": "https://s2.dmcdn.net/v/aKPyc1g428UiPL20b",
    "m3u8Url": "https://cdndirector.dailymotion.com/cdn/manifest/video/xa2s17q.m3u8?sec=v0vi8mcHKJYHnSemKtYCk--WAzmVOH8vzbW6umDwCKhmdx5eNX2ndbyCMXfMtiHltgjtoZjhlwu7FoOIucHG8A&dmTs=420009&dmV1st=B875E90F44BD9CC9DF45F2044E52745E",
    "embedUrl": "https://www.dailymotion.com/embed/video/xa2s17q",
    "duration": 5433,
    "views": 41845,
    "uploadedAt": "2026-03-20T05:34:48.000Z",
    "timestamp": 1773984888
  },
  {
    "id": "xa2s0de",
    "title": "بعد إغلاق البسطة صرت وريثًا",
    "thumbnail": "https://s2.dmcdn.net/v/aKPhY1fq3ACtwIhXN",
    "m3u8Url": "https://cdndirector.dailymotion.com/cdn/manifest/video/xa2s0de.m3u8?sec=WI981Mtxsp9uQ3bWQjW07AlPNeGazc-nkR2DaR-pthrbqXVXSagv9hvHxbudQ92bG0cCgypaOpopo2sqX-zkag&dmTs=655321&dmV1st=3D81080021E0634E977E35F22B82726D",
    "embedUrl": "https://www.dailymotion.com/embed/video/xa2s0de",
    "duration": 4486,
    "views": 38024,
    "uploadedAt": "2026-03-20T05:16:13.000Z",
    "timestamp": 1773983773
  },
  {
    "id": "xa2p4bc",
    "title": "الصبر مدبلج النهاية",
    "thumbnail": "https://s1.dmcdn.net/v/aJumO1g41yikrAu_g",
    "m3u8Url": "https://cdndirector.dailymotion.com/cdn/manifest/video/xa2p4bc.m3u8?sec=x-00h3mASulBv0FIw_nAUbrDrwsNCe7u_xRvWm_TAho2WK2JNJ0vQsMLfQDxNYSpa4qNASCHTskJuESKZM24ZQ&dmTs=72310&dmV1st=A4A0220938A982C515568D973165379B",
    "embedUrl": "https://www.dailymotion.com/embed/video/xa2p4bc",
    "duration": 1567,
    "views": 30998,
    "uploadedAt": "2026-03-19T23:30:54.000Z",
    "timestamp": 1773963054
  },
  {
    "id": "xa2oiim",
    "title": "الصبر 1 مدبلج",
    "thumbnail": "https://s1.dmcdn.net/v/aJns-1g3tSqrbN5gD",
    "m3u8Url": "https://cdndirector.dailymotion.com/cdn/manifest/video/xa2oiim.m3u8?sec=k7y8JyBPUuDck4zc7IiPsTX5M9mAfsosrsS8GZhqdSBCKOTmpAQGZuFs6GsXH6aViQKJYHhW8cnUB4ncfUxMjA&dmTs=884733&dmV1st=33FD6A37F78FD44EBD487AFBE9C646A1",
    "embedUrl": "https://www.dailymotion.com/embed/video/xa2oiim",
    "duration": 2278,
    "views": 31944,
    "uploadedAt": "2026-03-19T17:10:26.000Z",
    "timestamp": 1773940226
  },
  {
    "id": "xa2iy9c",
    "title": "سر منزلي",
    "thumbnail": "https://s2.dmcdn.net/v/aIoVm1frlojZD0UWx",
    "m3u8Url": "https://cdndirector.dailymotion.com/cdn/manifest/video/xa2iy9c.m3u8?sec=FivlDqJhi_nMLI_Ag2oU_dFilnFN4O7NsLczQWyPJjrY1oN5HS1MGFNfNRKwkiz_yZBsT8jCVBL9fKVaXXg6ew&dmTs=593900&dmV1st=5BA67C9E9A6EC66E4608D12CE06ADB01",
    "embedUrl": "https://www.dailymotion.com/embed/video/xa2iy9c",
    "duration": 5451,
    "views": 11070,
    "uploadedAt": "2026-03-18T19:19:58.000Z",
    "timestamp": 1773861598
  },
  {
    "id": "xa2ix64",
    "title": "لا تدللني يا زوجي… فأنا الوريثة المزيفة",
    "thumbnail": "https://s2.dmcdn.net/v/aIo9i1fnH_mhxJA7U",
    "m3u8Url": "https://cdndirector.dailymotion.com/cdn/manifest/video/xa2ix64.m3u8?sec=_naH9n5pNU1a_QHCh0qUonUeG4o8fS27V4g_zFMFrlbpRrntTPPulevqzz_lgY0iecwDrw3CfyLcP_6YN_jpsw&dmTs=962684&dmV1st=5C1C4E5F844B7FFA88A75851AEF5EDDC",
    "embedUrl": "https://www.dailymotion.com/embed/video/xa2ix64",
    "duration": 6326,
    "views": 38265,
    "uploadedAt": "2026-03-18T18:41:49.000Z",
    "timestamp": 1773859309
  },
  {
    "id": "xa2gv9i",
    "title": "[مدبلج]قتال",
    "thumbnail": "https://s1.dmcdn.net/v/aIQn61fpK5o5qDYoG",
    "m3u8Url": "https://cdndirector.dailymotion.com/cdn/manifest/video/xa2gv9i.m3u8?sec=_wQ7ZIf_z3lu3BEVmBqpuY_Tc-rMDea2340J6nRQbj_1KvT2yc0D-0UFj9GQdHJy6zIPPmFaSEaMC2SNa7DwrA&dmTs=682031&dmV1st=AE71AC4FD94B919408221688FEFCAC48",
    "embedUrl": "https://www.dailymotion.com/embed/video/xa2gv9i",
    "duration": 3560,
    "views": 27228,
    "uploadedAt": "2026-03-18T16:51:02.000Z",
    "timestamp": 1773852662
  },
  {
    "id": "xa2glco",
    "title": "عروس أمير مصاص الدماء",
    "thumbnail": "https://s1.dmcdn.net/v/aINeO1g41efQy2Hn9",
    "m3u8Url": "https://cdndirector.dailymotion.com/cdn/manifest/video/xa2glco.m3u8?sec=K_423OeJttZifYcWiLDom1g3hhgbfJU4dJbvmVnVaZfzOIIQ3CbumTAxzIlOEBodjeikEblhAB-4SP-dcUgOEA&dmTs=471485&dmV1st=22F873D8F3D02E7F6D71A514AEE1859C",
    "embedUrl": "https://www.dailymotion.com/embed/video/xa2glco",
    "duration": 5116,
    "views": 1127,
    "uploadedAt": "2026-03-18T16:22:17.000Z",
    "timestamp": 1773850937
  },
  {
    "id": "xa2gey0",
    "title": "خيانة العروس  بين السم والفخ",
    "thumbnail": "https://s1.dmcdn.net/v/aILce1g41l2-MRRUp",
    "m3u8Url": "https://cdndirector.dailymotion.com/cdn/manifest/video/xa2gey0.m3u8?sec=5-s5Ti11b_zYjyAIwie1AiCevf2APyBbwe-sXB09HcF3nH3L4qek0fl_Z-qGeeQxPeMvRSP-m4lV_5NgbkSUNw&dmTs=731997&dmV1st=53CD78FB0C20657A8E47D875FC08CDC2",
    "embedUrl": "https://www.dailymotion.com/embed/video/xa2gey0",
    "duration": 4636,
    "views": 11629,
    "uploadedAt": "2026-03-18T15:33:29.000Z",
    "timestamp": 1773848009
  },
  {
    "id": "xa2f7bu",
    "title": "حب مشتعل[ مدبلج ]",
    "thumbnail": "https://s2.dmcdn.net/v/aI7pQ1flkBCv6ULdA",
    "m3u8Url": "https://cdndirector.dailymotion.com/cdn/manifest/video/xa2f7bu.m3u8?sec=GjpaHBpiMtbYD2j8ujVc9YPt3uQV4WXsT6zPy5jxj8XVlDikGtkr66IwLL1yWN2cH8H6gEYBm-fsmBKvpldPQg&dmTs=436234&dmV1st=CEF2D178EB99A1DD63B8205189379DE4",
    "embedUrl": "https://www.dailymotion.com/embed/video/xa2f7bu",
    "duration": 4245,
    "views": 11375,
    "uploadedAt": "2026-03-18T14:30:37.000Z",
    "timestamp": 1773844237
  },
  {
    "id": "xa2ec56",
    "title": "القائد السري للمفاتيح الخمس[ مدبلج ]",
    "thumbnail": "https://s1.dmcdn.net/v/aHzxw1g3lykYq6YsC",
    "m3u8Url": "https://cdndirector.dailymotion.com/cdn/manifest/video/xa2ec56.m3u8?sec=8nY1sKAoUfoyAvxzHfXhrmKkf81vfMK5Kd9v-zvvZhUhO7Wl7Mf7CtyujdfRuRUOh5v_o72L5UJsfI7s4gcpzQ&dmTs=103058&dmV1st=00CE27799249E9239912AB8A552E8FAE",
    "embedUrl": "https://www.dailymotion.com/embed/video/xa2ec56",
    "duration": 4703,
    "views": 1288,
    "uploadedAt": "2026-03-18T14:02:02.000Z",
    "timestamp": 1773842522
  },
  {
    "id": "xa2e5uo",
    "title": "زوجي السابق يرحل عن عالمي",
    "thumbnail": "https://s2.dmcdn.net/v/aHxyW1fn80-1fEzCS",
    "m3u8Url": "https://cdndirector.dailymotion.com/cdn/manifest/video/xa2e5uo.m3u8?sec=_sGQOUmqEfIoLl2IoFlY_kl1rw_wKu3-f0t70XzjT3ZR6I3R7R0pRYisoRazNcBi-K1fimzg1tzLvDN0IX-QdQ&dmTs=617191&dmV1st=CB0A66F3517ECD2B69E3CB8BC187A1D9",
    "embedUrl": "https://www.dailymotion.com/embed/video/xa2e5uo",
    "duration": 5522,
    "views": 34960,
    "uploadedAt": "2026-03-18T13:25:07.000Z",
    "timestamp": 1773840307
  },
  {
    "id": "xa2dk1s",
    "title": "الحب رقصة خطيرة",
    "thumbnail": "https://s1.dmcdn.net/v/aHr301g41LM3pqJq3",
    "m3u8Url": "https://cdndirector.dailymotion.com/cdn/manifest/video/xa2dk1s.m3u8?sec=M5STTqdYgO_OsnzieD2rsGtUaadSwE68oXqv9ZfubWvWoT3onZcdnyD5m1aZOjiubszX84VqhWz_seMY37SqwA&dmTs=890129&dmV1st=F802F4C971A8CD40D72644096C978C1F",
    "embedUrl": "https://www.dailymotion.com/embed/video/xa2dk1s",
    "duration": 5738,
    "views": 3181,
    "uploadedAt": "2026-03-18T12:38:52.000Z",
    "timestamp": 1773837532
  },
  {
    "id": "xa2c53u",
    "title": "عودة عامل النظافة الملياردير[ مدبلج ]",
    "thumbnail": "https://s1.dmcdn.net/v/aHaxQ1gCEehzFwZF9",
    "m3u8Url": "https://cdndirector.dailymotion.com/cdn/manifest/video/xa2c53u.m3u8?sec=rSloBaXThEStmQ2oBB8PnTFzH3NzsXQX3Y5gofWvV_7Z1dFAc4Zfz3v0P85b_AOJiKJ82lt33iLCDpmTK-huxQ&dmTs=665303&dmV1st=409E54E986E65FE29101362D78528359",
    "embedUrl": "https://www.dailymotion.com/embed/video/xa2c53u",
    "duration": 5117,
    "views": 1701,
    "uploadedAt": "2026-03-18T11:58:55.000Z",
    "timestamp": 1773835135
  },
  {
    "id": "xa28jz4",
    "title": "مدبلج   زواج ينمو بين الأشواك   prt 3",
    "thumbnail": "https://s2.dmcdn.net/v/aGy4W1g425FH5iClj",
    "m3u8Url": "https://cdndirector.dailymotion.com/cdn/manifest/video/xa28jz4.m3u8?sec=pdvVzQGGZoKd3JsItjDo_F_H-iGkMSn9mxYDh_Gz08Q6XFnI6ljedJp4Vgv0Pm2k9TAnA9baVCL3X05KHiHITg&dmTs=232863&dmV1st=EF4DC56BBC8977FFE32CA901BED40576",
    "embedUrl": "https://www.dailymotion.com/embed/video/xa28jz4",
    "duration": 2735,
    "views": 48297,
    "uploadedAt": "2026-03-18T00:40:45.000Z",
    "timestamp": 1773794445
  },
  {
    "id": "xa28j2w",
    "title": "مدبلج   زواج ينمو بين الأشواك   prt 2",
    "thumbnail": "https://s1.dmcdn.net/v/aGxoO1fkeyFuoqdaB",
    "m3u8Url": "https://cdndirector.dailymotion.com/cdn/manifest/video/xa28j2w.m3u8?sec=godh4x8kcjQXpAey4x5HR8qoV8eA5oJnJ1VeEn8ffEat-V2a3DD25xUUFEOTguHU0uTgmYHWNUZ8MhDwz8M_zQ&dmTs=952280&dmV1st=298174EBF32EAA1209B8DCADA73156B0",
    "embedUrl": "https://www.dailymotion.com/embed/video/xa28j2w",
    "duration": 2648,
    "views": 4101,
    "uploadedAt": "2026-03-18T00:20:14.000Z",
    "timestamp": 1773793214
  },
  {
    "id": "xa28awq",
    "title": "مدبلج   زواج ينمو بين الأشواك   prt 1",
    "thumbnail": "https://s2.dmcdn.net/v/aGvCw1g425Vlnr3Nl",
    "m3u8Url": "https://cdndirector.dailymotion.com/cdn/manifest/video/xa28awq.m3u8?sec=5odUZybvUwQ4zmcftg-GikgWZVkdqteaXZJuiTzaA3IfCb1qE5wqMrZIiZHdeES-nyKw55W4QCSWzNO3cq4OIg&dmTs=683966&dmV1st=84ACB51827A248C3770B51C7E13628E0",
    "embedUrl": "https://www.dailymotion.com/embed/video/xa28awq",
    "duration": 2590,
    "views": 15979,
    "uploadedAt": "2026-03-17T21:39:13.000Z",
    "timestamp": 1773783553
  },
  {
    "id": "xa26x3a",
    "title": "أنفِق ... لتَسُود",
    "thumbnail": "https://s1.dmcdn.net/v/aGfS61fkau7UJy9KR",
    "m3u8Url": "https://cdndirector.dailymotion.com/cdn/manifest/video/xa26x3a.m3u8?sec=THXda056sD5Ocoop4Xw_6uwf24wiVsQBkAyVgTw0u9p_GV7wAT2waXLAtDP-HH1LJugEPY7_vSeQ3COo3Ok2AA&dmTs=681778&dmV1st=DC284070CF69B7EABFB8033AEB5CAF9E",
    "embedUrl": "https://www.dailymotion.com/embed/video/xa26x3a",
    "duration": 6372,
    "views": 34736,
    "uploadedAt": "2026-03-17T13:18:09.000Z",
    "timestamp": 1773753489
  },
  {
    "id": "xa26qv4",
    "title": "بين الحب والسلاح",
    "thumbnail": "https://s1.dmcdn.net/v/aGdU01g41ycBknQZZ",
    "m3u8Url": "https://cdndirector.dailymotion.com/cdn/manifest/video/xa26qv4.m3u8?sec=wVsAVn2wKEj9Jz6ZaY_eNonOyPVZMzyISwpSJUWN62uoPdD4YaKhDG19Xo5dmlyOIBHqoJghkOAKTLe4Fraozg&dmTs=221333&dmV1st=B5DE38096A5A0DF034E430653D538594",
    "embedUrl": "https://www.dailymotion.com/embed/video/xa26qv4",
    "duration": 5537,
    "views": 49296,
    "uploadedAt": "2026-03-17T12:05:53.000Z",
    "timestamp": 1773749153
  },
  {
    "id": "xa269n8",
    "title": "قطع السيف عبر الأزمان",
    "thumbnail": "https://s2.dmcdn.net/v/aGY1K1fkIoF0FHKMO",
    "m3u8Url": "https://cdndirector.dailymotion.com/cdn/manifest/video/xa269n8.m3u8?sec=hR1qqK2qiQOmlD6ZBbmbTYOKRStpslIBFp4mDZmMNLzJIqP859O366piaL66yhfz8vg2sR63fwMqZ9Ry2Kc33w&dmTs=818845&dmV1st=5733499FE10AF5D468F1C1EF6F8E8409",
    "embedUrl": "https://www.dailymotion.com/embed/video/xa269n8",
    "duration": 4670,
    "views": 1260,
    "uploadedAt": "2026-03-17T08:50:50.000Z",
    "timestamp": 1773737450
  },
  {
    "id": "xa23fck",
    "title": "تكره فاطمة السم",
    "thumbnail": "https://s2.dmcdn.net/v/aG1fq1g3YRsIWJ9rs",
    "m3u8Url": "https://cdndirector.dailymotion.com/cdn/manifest/video/xa23fck.m3u8?sec=SvCrw5lBcWUOav8VT8hpCi5jpAi3N4xQLyMVCkbjkMzc8E-LvYj4nuiDHKgFpTxNk8Y69w-TCCC2KrFOjlDH7g&dmTs=908064&dmV1st=A81D6E1D27FC6DC0A63CA638EA5E75C4",
    "embedUrl": "https://www.dailymotion.com/embed/video/xa23fck",
    "duration": 6586,
    "views": 18625,
    "uploadedAt": "2026-03-16T11:40:49.000Z",
    "timestamp": 1773661249
  }
]