{
  "id": "192947",
  "title": "فيلم Anaconda 2025 مترجم اون لاين",
  "url": "https://topcinema.rip/%d9%81%d9%8a%d9%84%d9%85-anaconda-2025-%d9%85%d8%aa%d8%b1%d8%ac%d9%85-%d8%a7%d9%88%d9%86-%d9%84%d8%a7%d9%8a%d9%86/",
  "shortLink": "https://topcinema.rip/?p=192947",
  "image": "https://topcinema.rip/wp-content/uploads/2026/01/MV5BMTNlMTk1YTItOWYxNi00ZWIzLTkyOWEtNTJmMzk4NmIyN2NmXkEyXkFqcGc@.jpg_V1_SX700-433x650.jpg",
  "imdbRating": "6.1",
  "story": "وسط معاناة أزمة منتصف العمر، تقرر مجموعة من الأصدقاء التعاون معًا في سبيل إنتاج نسخة حديثة من فيلمهم المفضل بفترة الشباب، ولكن تقودهم الرحلة إلى مجموعة من الأحداث الغير متوقعة بالأدغال.",
  "details": {
    "قسم الفيلم": [
      "افلام اجنبي"
    ],
    "نوع الفيلم": [
      "اكشن",
      "كوميدي",
      "مغامرة"
    ],
    "جودة الفيلم": [
      "720p HDTS"
    ],
    "توقيت الفيلم": "1 ساعة و 39 دقيقة",
    "موعد الصدور": [
      "2025"
    ],
    "دولة الفيلم": [
      "الولايات المتحدة الامريكية"
    ],
    "بطولة": [
      "Anna Francesca Armenia",
      "Dan Silveira",
      "Daniela Melchior",
      "Diego Arnary"
    ]
  },
  "watchPage": "https://topcinema.rip/%d9%81%d9%8a%d9%84%d9%85-anaconda-2025-%d9%85%d8%aa%d8%b1%d8%ac%d9%85-%d8%a7%d9%88%d9%86-%d9%84%d8%a7%d9%8a%d9%86/watch/",
  "watchServer": {
    "type": "embed",
    "url": "https://topcinema.rip/%d9%81%d9%8a%d9%84%d9%85-anaconda-2025-%d9%85%d8%aa%d8%b1%d8%ac%d9%85-%d8%a7%d9%88%d9%86-%d9%84%d8%a7%d9%8a%d9%86/?embedScreen=true",
    "source": "meta_tag"
  },
  "downloadPage": "https://topcinema.rip/%d9%81%d9%8a%d9%84%d9%85-anaconda-2025-%d9%85%d8%aa%d8%b1%d8%ac%d9%85-%d8%a7%d9%88%d9%86-%d9%84%d8%a7%d9%8a%d9%86/download/",
  "downloadServers": {
    "multiQuality": [
      {
        "name": "VidTube",
        "url": "https://vidtube.one/d/82swu2t5xp58.html",
        "type": "multi_quality"
      }
    ],
    "byQuality": {
      "720p": [
        {
          "name": "UpDown",
          "quality": "720p",
          "url": "https://updown.cam/1juca8005zwl"
        },
        {
          "name": "Mdiaload",
          "quality": "720p",
          "url": "https://down.mdiaload.com/u58cqbvphw0z"
        },
        {
          "name": "Ddownload",
          "quality": "720p",
          "url": "https://ddownload.com/3jy61wdxyvuf"
        },
        {
          "name": "Nitroflare",
          "quality": "720p",
          "url": "https://nitroflare.com/view/89863221F1079BD"
        },
        {
          "name": "1Fichier",
          "quality": "720p",
          "url": "https://1fichier.com/?b6iu5kccd8uphfhx0o4u"
        },
        {
          "name": "Rapidgator",
          "quality": "720p",
          "url": "https://rapidgator.net/file/2fec95998a48dd564f795f6c32b37d8a"
        },
        {
          "name": "Freedl",
          "quality": "720p",
          "url": "https://frdl.io/ywyporihrlc6"
        },
        {
          "name": "CloudFile",
          "quality": "720p",
          "url": "https://1cloudfile.com/2auli"
        }
      ]
    }
  },
  "page": 1,
  "scrapedAt": "2026-01-25T14:11:39.391Z"
}